dredarkLeaderboardLib/__init__.py
dredarkLeaderboardLib/archive.py
dredarkLeaderboardLib/base.py
dredarkLeaderboardLib/checks.py
dredarkLeaderboardLib/errors.py
dredarkLeaderboardLib/legacy.py
dredarkLeaderboardLib-2.0.3.post3.dist-info/LICENSE
dredarkLeaderboardLib-2.0.3.post3.dist-info/METADATA
dredarkLeaderboardLib-2.0.3.post3.dist-info/WHEEL
dredarkLeaderboardLib-2.0.3.post3.dist-info/top_level.txt
dredarkLeaderboardLib-2.0.3.post3.dist-info/RECORD
