Metadata-Version: 2.1
Name: dredarkLeaderboardLib
Version: 2.0.3.post3
Summary: A Library to fetch from the Deep Space Airships leaderboards.
Author: JaWarrior12
License: MIT License
Project-URL: Homepage, https://github.com/JaWarrior12/dredarkLeaderboardLib
Project-URL: Issues, https://github.com/JaWarrior12/dredarkLeaderboardLib/issues
Project-URL: Wiki, https://github.com/JaWarrior12/dredarkLeaderboardLib/wiki
Project-URL: Discord, https://discord.gg/WGmCS7pJ48
Keywords: dredark.io,drednot.io,drednot,dredark,deep space airships,jawarrior,jamwarior,leaderboard
Classifier: Development Status :: 3 - Alpha
Classifier: Programming Language :: Python :: 3
Classifier: License :: OSI Approved :: MIT License
Classifier: Operating System :: OS Independent
Classifier: Natural Language :: English
Requires-Python: >=3.10
License-File: LICENSE
Requires-Dist: beautifulsoup4 >=4.12.3
Requires-Dist: bs4 >=0.0.2
Requires-Dist: certifi >=2024.8.30
Requires-Dist: charset-normalizer >=3.3.2
Requires-Dist: idna >=3.8
Requires-Dist: requests >=2.32.3
Requires-Dist: soupsieve >=2.6
Requires-Dist: urllib3 >=2.2.3
